edgetest/__init__.py
edgetest/core.py
edgetest/hookspecs.py
edgetest/interface.py
edgetest/lib.py
edgetest/logger.py
edgetest/report.py
edgetest/schema.py
edgetest/utils.py
edgetest-2026.1.1.dist-info/licenses/AUTHORS.md
edgetest-2026.1.1.dist-info/licenses/LICENSE
edgetest-2026.1.1.dist-info/METADATA
edgetest-2026.1.1.dist-info/WHEEL
edgetest-2026.1.1.dist-info/entry_points.txt
edgetest-2026.1.1.dist-info/top_level.txt
edgetest-2026.1.1.dist-info/RECORD
