Metadata-Version: 2.4
Name: edgetest
Version: 2026.1.1
Summary: Bleeding edge dependency testing
Author-email: Akshay Gupta <akshay.gupta2@capitalone.com>, Faisal Dosani <faisal.dosani@capitalone.com>, Jacob Dawang <jacob.dawang@capitalone.com>
License: Apache Software License
Project-URL: Bug Tracker, https://github.com/capitalone/edgetest/issues
Project-URL: Documentation, https://capitalone.github.io/edgetest/
Project-URL: Source Code, https://github.com/capitalone/edgetest
Classifier: Intended Audience :: Developers
Classifier: Natural Language :: English
Classifier: Operating System :: OS Independent
Classifier: Programming Language :: Python
Classifier: Programming Language :: Python :: 3 :: Only
Classifier: Programming Language :: Python :: 3.10
Classifier: Programming Language :: Python :: 3.11
Classifier: Programming Language :: Python :: 3.12
Requires-Python: >=3.10
License-File: LICENSE
License-File: AUTHORS.md
Requires-Dist: cerberus<=1.3.8,>=1.3.5
Requires-Dist: click<=8.3.1,>=7.0
Requires-Dist: packaging<=26.0,>20.6
Requires-Dist: pluggy<=1.6.0,>=1.5.0
Requires-Dist: pyproject-fmt<=2.11.1,>=2.0.0
Requires-Dist: tabulate<=0.9.0,>=0.8.9
Requires-Dist: tomlkit<=0.14.0,>=0.11.4
Requires-Dist: uv<=0.9.26,>=0.6.0
Provides-Extra: build
Requires-Dist: build; extra == "build"
Requires-Dist: bumpver; extra == "build"
Requires-Dist: twine; extra == "build"
Requires-Dist: wheel; extra == "build"
Provides-Extra: dev
Requires-Dist: edgetest[build]; extra == "dev"
Requires-Dist: edgetest[docs]; extra == "dev"
Requires-Dist: edgetest[qa]; extra == "dev"
Requires-Dist: edgetest[tests]; extra == "dev"
Provides-Extra: docs
Requires-Dist: furo; extra == "docs"
Requires-Dist: pillow; extra == "docs"
Requires-Dist: recommonmark; extra == "docs"
Requires-Dist: sphinx; extra == "docs"
Requires-Dist: sphinx-copybutton; extra == "docs"
Requires-Dist: sphinx-tabs; extra == "docs"
Provides-Extra: qa
Requires-Dist: mypy; extra == "qa"
Requires-Dist: pre-commit; extra == "qa"
Requires-Dist: ruff~=0.5; extra == "qa"
Requires-Dist: types-click; extra == "qa"
Requires-Dist: types-setuptools; extra == "qa"
Requires-Dist: types-tabulate; extra == "qa"
Provides-Extra: tests
Requires-Dist: coverage; extra == "tests"
Requires-Dist: pytest; extra == "tests"
Requires-Dist: pytest-cov; extra == "tests"
Dynamic: license-file
